include/liquibook/liquibook_export.h
include/liquibook/book/bbo_listener.h
include/liquibook/book/callback.h
include/liquibook/book/comparable_price.h
include/liquibook/book/depth.h
include/liquibook/book/depth_constants.h
include/liquibook/book/depth_level.h
include/liquibook/book/depth_listener.h
include/liquibook/book/depth_order_book.h
include/liquibook/book/logger.h
include/liquibook/book/order.h
include/liquibook/book/order_book.h
include/liquibook/book/order_book_listener.h
include/liquibook/book/order_listener.h
include/liquibook/book/order_tracker.h
include/liquibook/book/trade_listener.h
include/liquibook/book/types.h
include/liquibook/book/version.h
include/liquibook/simple/simple_order.h
include/liquibook/simple/simple_order_book.h
liquibook/__init__.py
liquibook/__liquibook.so
liquibook/_liquibook.py
liquibook/helpers/__init__.py
liquibook/helpers/json_serializer.py
liquibook/helpers/pretty_print.py
liquibook-2.0.1.dist-info/METADATA
liquibook-2.0.1.dist-info/WHEEL
liquibook-2.0.1.dist-info/RECORD
