Metadata-Version: 2.2
Name: liquibook
Version: 2.0.1
Summary: Python wrapper for LiquiBook - Order Matching Engine and Market Data
Author-Email: Mike Kipnis <mike.kipnis@gmail.com>
Requires-Python: >=3.8
